README.rst
setup.py
probe/__init__.py
probe/mc/__init__.py
probe/mc/integrator.py
probe/mc/integrator_runner.py
probe/mc/mc.f90
probe/mc/ziggurat.f90
probe_mc_analytic_er.egg-info/PKG-INFO
probe_mc_analytic_er.egg-info/SOURCES.txt
probe_mc_analytic_er.egg-info/dependency_links.txt
probe_mc_analytic_er.egg-info/entry_points.txt
probe_mc_analytic_er.egg-info/namespace_packages.txt
probe_mc_analytic_er.egg-info/requires.txt
probe_mc_analytic_er.egg-info/top_level.txt
probe_mc_analytic_er.egg-info/zip-safe
scripts/mc.py