Metadata-Version: 1.0
Name: probe-mc-analytic-er
Version: 0.0.2
Summary: Monte Carlo simulation of particle motion in analytic radial field
Home-page: UNKNOWN
Author: Petr Zikan
Author-email: zikan.p@gmail.com
License: GPLv3
Platform: UNKNOWN
